aws_cdk_build_badge/__init__.py
aws_cdk_build_badge/py.typed
aws_cdk_build_badge/_jsii/__init__.py
aws_cdk_build_badge/_jsii/aws-cdk-build-badge@1.97.21.jsii.tgz
aws_cdk_build_badge-1.97.21.dist-info/LICENSE
aws_cdk_build_badge-1.97.21.dist-info/METADATA
aws_cdk_build_badge-1.97.21.dist-info/WHEEL
aws_cdk_build_badge-1.97.21.dist-info/top_level.txt
aws_cdk_build_badge-1.97.21.dist-info/RECORD
