Metadata-Version: 2.1
Name: aws-cdk-build-badge
Version: 1.97.21
Summary: aws-cdk-build-badge
Home-page: https://github.com/mmuller88/aws-cdk-build-badge
Author: martin.mueller<damadden88@googlemail.de>
License: Apache-2.0
Project-URL: Source, https://github.com/mmuller88/aws-cdk-build-badge
Platform: UNKNOWN
Classifier: Intended Audience :: Developers
Classifier: Operating System :: OS Independent
Classifier: Programming Language :: JavaScript
Classifier: Programming Language :: Python :: 3 :: Only
Classifier: Programming Language :: Python :: 3.6
Classifier: Programming Language :: Python :: 3.7
Classifier: Programming Language :: Python :: 3.8
Classifier: Programming Language :: Python :: 3.9
Classifier: Typing :: Typed
Classifier: Development Status :: 5 - Production/Stable
Classifier: License :: OSI Approved
Requires-Python: >=3.6
Requires-Dist: aws-cdk.aws-apigateway (==1.106.1)
Requires-Dist: aws-cdk.aws-iam (==1.106.1)
Requires-Dist: aws-cdk.aws-lambda-nodejs (==1.106.1)
Requires-Dist: aws-cdk.aws-lambda (==1.106.1)
Requires-Dist: aws-cdk.core (==1.106.1)
Requires-Dist: constructs (<4.0.0,>=3.2.27)
Requires-Dist: jsii (<2.0.0,>=1.29.0)
Requires-Dist: publication (>=0.0.3)
